tests/__init__.py
tests/test_api.py
xlsx_from_json/__init__.py
xlsx_from_json/api.py
xlsx_from_json/models.py
xlsx_from_json/utils.py
xlsx_from_json-1.0.1.dist-info/METADATA
xlsx_from_json-1.0.1.dist-info/RECORD
xlsx_from_json-1.0.1.dist-info/WHEEL
xlsx_from_json-1.0.1.dist-info/top_level.txt
