Metadata-Version: 2.1
Name: xlsx-from-json
Version: 1.0.1
Summary: Creates xlsx from json via openpyxl.
Home-page: https://github.com/potykion/xlsx_from_json
Author: potykion
Author-email: potykion@gmail.com
License: UNKNOWN
Platform: UNKNOWN
Classifier: Programming Language :: Python :: 3
Classifier: License :: OSI Approved :: MIT License
Classifier: Operating System :: OS Independent
Requires-Dist: attrs (>=18.1.0)
Requires-Dist: openpyxl (>=2.5.4)
